LICENSE.txt
MANIFEST.in
README.txt
setup.py
mood/__init__.py
mood.event.egg-info/PKG-INFO
mood.event.egg-info/SOURCES.txt
mood.event.egg-info/dependency_links.txt
mood.event.egg-info/namespace_packages.txt
mood.event.egg-info/not-zip-safe
mood.event.egg-info/top_level.txt
src/Async.c
src/Check.c
src/Child.c
src/Embed.c
src/Fork.c
src/Idle.c
src/Io.c
src/Loop.c
src/Periodic.c
src/Prepare.c
src/Scheduler.c
src/Signal.c
src/Timer.c
src/_Watcher.c
src/event.c
src/helpers/helpers.c