Metadata-Version: 1.2
Name: mood.event
Version: 1.1.0
Summary: Python libev interface
Home-page: https://github.com/lekma/mood.event
Author: Malek Hadj-Ali
Author-email: lekmalek@gmail.com
License: GNU General Public License v3 (GPLv3)
Download-URL: https://github.com/lekma/mood.event/releases
Project-URL: Bug Tracker, https://github.com/lekma/mood.event/issues
Project-URL: Documentation, https://mood.readthedocs.io/projects/event/
Keywords: libev event
Platform: POSIX
Classifier: Development Status :: 5 - Production/Stable
Classifier: Intended Audience :: Developers
Classifier: Intended Audience :: System Administrators
Classifier: License :: OSI Approved :: GNU General Public License v3 (GPLv3)
Classifier: Operating System :: POSIX
Classifier: Programming Language :: Python :: 3.5
Classifier: Programming Language :: Python :: Implementation :: CPython
Requires-Python: ~=3.5
